iso_forest.py
version.py
iso_forest-1.0.3.dist-info/DESCRIPTION.rst
iso_forest-1.0.3.dist-info/METADATA
iso_forest-1.0.3.dist-info/RECORD
iso_forest-1.0.3.dist-info/WHEEL
iso_forest-1.0.3.dist-info/metadata.json
iso_forest-1.0.3.dist-info/top_level.txt
