Metadata-Version: 2.0
Name: iso-forest
Version: 1.0.3
Summary: Isolation Forest for anomaly detection
Home-page: https://github.com/mgckind/iso_forest
Author: Matias Carrasco Kind
Author-email: mcarras2@illinois.edu
License: License.txt
Platform: UNKNOWN
Requires-Dist: numpy
